lark_webhook_notify/__init__.py
lark_webhook_notify/__main__.py
lark_webhook_notify/blocks.py
lark_webhook_notify/cli.py
lark_webhook_notify/client.py
lark_webhook_notify/config.py
lark_webhook_notify/convenience.py
lark_webhook_notify/py.typed
lark_webhook_notify/templates.py
lark_webhook_notify/workflow_templates.py
lark_webhook_notify-0.2.0.dist-info/METADATA
lark_webhook_notify-0.2.0.dist-info/WHEEL
lark_webhook_notify-0.2.0.dist-info/entry_points.txt
lark_webhook_notify-0.2.0.dist-info/licenses/LICENSE
lark_webhook_notify-0.2.0.dist-info/RECORD
