Metadata-Version: 2.4
Name: lark-webhook-notify
Version: 0.2.0
Summary: A Python library for sending notifications to Lark (Feishu) webhooks with configurable templates
Project-URL: Homepage, https://github.com/BobAnkh/lark-webhook-notify
Project-URL: Repository, https://github.com/BobAnkh/lark-webhook-notify
Project-URL: Source, https://github.com/BobAnkh/lark-webhook-notify
Author-email: BobAnkh <bobankhshen@gmail.com>
License: Apache-2.0
License-File: LICENSE
Keywords: Client,feishu,lark,messaging,notification,template,webhook
Classifier: Development Status :: 4 - Beta
Classifier: Intended Audience :: Developers
Classifier: License :: OSI Approved :: Apache Software License
Classifier: Operating System :: OS Independent
Classifier: Programming Language :: Python :: 3
Classifier: Programming Language :: Python :: 3 :: Only
Classifier: Programming Language :: Python :: 3.10
Classifier: Programming Language :: Python :: 3.11
Classifier: Programming Language :: Python :: 3.12
Classifier: Programming Language :: Python :: 3.13
Classifier: Topic :: Communications
Classifier: Topic :: Software Development :: Libraries :: Python Modules
Classifier: Topic :: Utilities
Requires-Python: >=3.10
Requires-Dist: colorlog>=6.10.1
Requires-Dist: httpx>=0.28.1
Requires-Dist: pydantic-settings>=2.10.1
Requires-Dist: pydantic>=2.11.7
